timekill/__init__.py
timekill/__main__.py
timekill/classify/__init__.py
timekill/classify/example_content.py
timekill/classify/gpt3.py
timekill/emoji.py
timekill/load/__init__.py
timekill/load/reddit.py
timekill/main.py
timekill/models.py
timekill/motivation.py
timekill/notify.py
timekill/py.typed
timekill/server.py
timekill/suggest/__init__.py
timekill/suggest/activities.py
timekill/suggest/models.py
timekill/suggest/schedule.py
timekill/suggest/suggest.py
timekill/test/test_classify.py
timekill/test/test_load.py
timekill-0.1.0.dist-info/entry_points.txt
timekill-0.1.0.dist-info/WHEEL
timekill-0.1.0.dist-info/METADATA
timekill-0.1.0.dist-info/RECORD
