Metadata-Version: 2.1
Name: timekill
Version: 0.1.0
Summary: A better way to kill time
Author: Erik Bjäreholt
Author-email: erik@bjareho.lt
Requires-Python: >=3.10,<3.12
Classifier: Programming Language :: Python :: 3
Classifier: Programming Language :: Python :: 3.10
Classifier: Programming Language :: Python :: 3.11
Requires-Dist: click (>=8.1.3,<9.0.0)
Requires-Dist: desktop-notifier (>=3.4.0,<4.0.0)
Requires-Dist: fastapi (>=0.85.0,<0.86.0)
Requires-Dist: joblib (>=1.2.0,<2.0.0)
Requires-Dist: openai (>=0.23.1,<0.24.0)
Requires-Dist: pandas (>=1.5.0,<2.0.0)
Requires-Dist: praw (>=7.6.0,<8.0.0)
Requires-Dist: requests (>=2.28.1,<3.0.0)
Requires-Dist: uvicorn[standard] (>=0.18.3,<0.19.0)
